{
    "상도동 황우와꿀꿀이": "소갈비살",
    "상도동 비비큐치킨상도점": "황금올리브반반+황금알치즈볼",
    "상도동 춘천닭갈비": "춘천닭갈비 (1인분)",
    "상도동 고향팥칼국수": "팥칼국수",
    "상도동 포안베트남쌀국수": "소고기쌀국수",
    "상도동 고기스토리": "국내산 특생삼겹살 (200g)",
    "상도동, 동일식당": "닭발",
    "상도동 옛골": "한방삼계탕",
    "상도동 기절초풍 물닭갈비": "얼씨구",
    "상도동 토방마루": "계란찜",
    "상도동 논두렁 갈비": "소 왕통갈비(1대)",
    "상도동 이삭김밥": "오징어김밥",
    "상도동 고향토종순대곱창": "순대국",
    "상도동 광명": "추천\n광명종합셋트",
    "상도동 함지박": "굴비백반",
    "상도동 포마토": "야채김밥",
    "상도동 불타는 소금구이": "소갈비살 (170g)",
    "상도동 시래불고기 화풍정": "시래불고기(1인)",
    "상도동 훌랄라숯불바베큐": "간장+정통후라이드",
    "상도동 우리풍천장어": "풍천민물장어(1인분)",
    "상도동 전주청국장": "청국장",
    "상도동 상투골": "동해 해물파전",
    "상도동 상도곱창": "소곱창 (1인분)",
    "상도동 이필배의 진짜루명태촌": "동태탕",
    "상도동 수제한식당": "철판제육볶음",
    "상도동 남도홍어": "참 조기 찌개",
    "상도동 성대생우동짜장": "짜면밥",
    "상도동 종로곱창": "막창소금(2인)",
    "상도동 황새골손칼국수": "해물손칼국수",
    "상도동 황궁쟁반짜장": "짜장면",
    "상도동 봉구스밥버거": "해봉이밥버거",
    "상도동 지호한방삼게탕동작점": "건강한방삼계탕",
    "상도동 우리할매 떡볶이(상도점)": "가래떡떡볶이",
    "상도동 약수 오리한마리": "소금구이",
    "상도동 남도한상": "참 조기 찌개",
    "상도동 또봉이통닭(상도점)": "또봉이통닭",
    "상도동 동네고깃집": "도가니탕",
    "상도동 돼지굽는연탄할매": "갈비살(180g)",
    "상도동 작은섬": "광어숙성회(중)",
    "상도동 아시안보울": "기본쌀국수",
    "상도동 으리으리": "차돌순두부(1인)",
    "상도동 국수사": "메뉴",
    "상도동 후라이드 참 잘하는 집": "후라이드",
    "상도동 시골집": "차돌배기",
    "상도동 짚동가리쌩주": "김치전",
    "상도동 불타는 꼬꼬발 숭실대점": "콜라겐 무뼈 닭발(소)",
    "상도동 가마솥장우왕족발": "미니족",
    "상도동 흥부골숯불돼지갈비": "돼지갈비 (250g)",
    "상도동 이모네": "제주 흑돼지 오겹(150g)",
    "상도동 상도면옥": "물냉면",
    "상도동 한양옛날통닭": "옛날통닭(한마리)",
    "상도동, 교동 전선생": "감자전",
    "상도동 비비엣": "소고기 쌀국수",
    "상도동 뽀대닭발 동작점": "통국물닭발 (중)",
    "상도동 파동추야": "무우전",
    "상도동 피자마루": "골드 치킨 텐더 피자",
    "상도동 리얼 후라이 숭실대점": "트리플치즈 텐더치킨",
    "상도동 남서울식당": "야채김밥",
    "상도동 할머니칼국수": "콩국수",
    "상도동, 할머니 추어탕": "추어탕+돌솥밥",
    "상도동 훈이네식당": "감자탕(소)",
    "상도동, 신정 닭발": "통닭발",
    "상도동, 뚝배기 스파게티": "베이컨과 카라멜 양파토마토소스 스파게티",
    "상도동 피자나라 치킨공주": "고구마피자(L)",
    "상도동 성대순대촌": "양념수대곱창(2인분)",
    "상도동 벌떡볶이": "벌떡볶이",
    "상도동 블랙조이커피": "아메리카노",
    "상도동 마루스시": "회덮밥",
    "상도동 탕마루김치찌개(장승배기역점)": "양푼 생고기 김치찌개",
    "상도동, 상도두산위브아파트 피자알볼로 상도점": "대새피자",
    "상도동 명성": "활어회(소)",
    "상도동 오븐마루상도점": "마루떡복이",
    "상도동 밀짚모자": "잔치국수",
    "상도동 미학당": "카페라떼",
    "상도동 마망베베 키즈카페 &  킨더레고팡": "토마토 모짜렐라 파스타",
    "상도동 우리보쌈&밥상": "우리보쌈(소)",
    "상도동 가마로강정 숭실대역점": "싱글",
    "상도동 우마이": "수제 돈까스 카레",
    "상도동 품미": "짬뽕",
    "상도동 디디치킨(DD치킨)": "매직버터치킨세트(보퉁맛)",
    "상도동 제이콜라보": "에스프레소",
    "상도동 스톤504": "수제 베이컨 시저 샐러드",
    "상도동 양계장집아들 상도점": "양아들 후라이드치킨",
    "상도동 마당커피": "아메리카노",
    "상도동 맨드라미": "삼계탕",
    "상도동 상도국수": "닭곰탕국수",
    "상도동 비에이치씨(BHC치킨) 상도점": "치퐁당 후라이드",
    "상도동 스시아나": "모듬초밥(10p)",
    "상도동 춘자씨칼국수": "손칼국수 (보)",
    "상도동 콩심신대방점": "콩나물국밥",
    "상도동 취향": "짜장면",
    "상도동 청춘싸롱 신대방삼거리역점": "그릴치킨스테끼",
    "상도동 장승칡냉면&장족": "물냉면",
    "상도동 카페 더테이블": "에스프레소",
    "상도동 지코바상도1호점": "지코바 소금구이",
    "상도동 청년떡볶이장승배기역점": "국물떡볶이",
    "상도동 강남교자상도점": "강남샤브샤브",
    "상도동 로드77": "치즈돈까스(2인분)",
    "상도동 명성왕족발": "앞다리살한마리(2~3인이상)",
    "상도동 구름산추어탕": "추어탕",
    "상도동 호식이두마리치킨상도1호점": "간장치킨",
    "상도동 대현포차": "메기 매운탕(소)",
    "상도동 커피온리 숭실대점": "아메리카노",
    "상도동 더진국숭실대점": "순대국밥",
    "상도동 오뚜기마당": "국물밀떡",
    "상도동 마왕족발": "마왕통구이",
    "상도동 내가찜한닭(숭실대점)": "순살안동찜닭(소)",
    "상도동 더코네(The kone)": "즉석떡볶이(2인)",
    "상도동 우니꾸": "토시살 (150g)",
    "상도동 복어마을": "복지리탕 (1인)",
    "상도동 추억과김밥": "원조김밥",
    "상도동 농장사람들": "꽃듬심 (150g)"
}